<?xml version="1.0" encoding="UTF-8"?>
<beans xmlns="http://www.springframework.org/schema/beans"
	xmlns:xsi="http://www.w3.org/2001/XMLSchema-instance"
	xsi:schemaLocation="http://www.springframework.org/schema/beans http://www.springframework.org/schema/beans/spring-beans.xsd">

	<bean id="entityManagerFactory"
		class="org.springframework.orm.jpa.LocalContainerEntityManagerFactoryBean">
		<property name="dataSource" ref="dataSource" />
		<property name="packagesToScan" value="${jpa.packagesToScan}" />
		<property name="jpaVendorAdapter">
			<bean class="org.springframework.orm.jpa.vendor.HibernateJpaVendorAdapter">
				<property name="showSql" value="${hibernate.show_sql}" />
				<property name="databasePlatform" value="${hibernate.dialect}" />
			</bean>
		</property>
		<property name="jpaProperties">
			<props>
				<prop key="hibernate.hbm2ddl.auto">
					${hibernate.hbm2ddl.auto}
				</prop>
			</props>
		</property>
	</bean>
	
	<!-- bean post-processor for JPA annotations -->
	<bean
		class="org.springframework.orm.jpa.support.PersistenceAnnotationBeanPostProcessor" />

	<!-- Exception translation bean post processor -->
	<bean
		class="org.springframework.dao.annotation.PersistenceExceptionTranslationPostProcessor" />


	<bean id="transactionManager" class="org.springframework.orm.jpa.JpaTransactionManager">
		<property name="entityManagerFactory" ref="entityManagerFactory" />
	</bean>

</beans>
